PyTFBS/__init__.py
PyTFBS/motif.py
PyTFBS/predict.py
pytfbs-1.0.2.dist-info/licenses/LICENSE
pytfbs-1.0.2.dist-info/METADATA
pytfbs-1.0.2.dist-info/WHEEL
pytfbs-1.0.2.dist-info/entry_points.txt
pytfbs-1.0.2.dist-info/top_level.txt
pytfbs-1.0.2.dist-info/RECORD
