Metadata-Version: 2.4
Name: PyTFBS
Version: 1.0.2
Summary: PyTFBS: A Python Package for Transcription Factor Binding Site Prediction
Author-email: Tinghua Huang <thua45@126.com>
License-Expression: MIT
Project-URL: Homepage, https://github.com/thua45/pytfbs
Project-URL: Documentation, https://github.com/thua45/pytfbs#readme
Project-URL: Repository, https://github.com/thua45/pytfbs
Project-URL: Issues, https://github.com/thua45/pytfbs/issues
Keywords: PyTFBS,Transcription Factor,Binding Site
Classifier: Development Status :: 4 - Beta
Classifier: Intended Audience :: Developers
Classifier: Programming Language :: Python :: 3.11
Classifier: Programming Language :: Python :: 3.12
Classifier: Programming Language :: Python :: 3.13
Requires-Python: >=3.11
License-File: LICENSE
Requires-Dist: torch
Requires-Dist: numpy==1.26; sys_platform == "darwin"
Requires-Dist: numpy>=2.0; sys_platform == "win32"
Requires-Dist: numpy>=2.0; sys_platform == "linux"
Provides-Extra: dev
Requires-Dist: matplotlib; extra == "dev"
Provides-Extra: test
Requires-Dist: matplotlib; extra == "test"
Dynamic: license-file
